{"is_source_file": true, "format": "JavaScript", "description": "This JavaScript module provides functions to interact with recipe data. It includes mock data for recipes, functions to list recipes with filtering options, retrieve a specific recipe by ID, save (create or update) recipes, and fetch available tags and cuisines for filtering. It exports an API interface for frontend components to consume recipe data.", "external_files": ["./client"], "external_methods": ["apiRequest"], "published": ["listRecipes", "getRecipe", "saveRecipe", "listTags", "listCuisines"], "classes": [], "methods": [{"name": "listRecipes(params = {})", "description": "Fetches a list of recipes, optionally filtering by search terms, tags, cuisine, time, difficulty, rating, pagination. Returns an array of recipe summaries.", "scope": "", "scopeKind": ""}, {"name": "getRecipe(id)", "description": "Retrieves a specific recipe by its ID. Returns the recipe object or null if not found.", "scope": "", "scopeKind": ""}, {"name": "saveRecipe(recipe)", "description": "Creates a new recipe or updates an existing one based on the presence of recipe.id. Returns the saved recipe object.", "scope": "", "scopeKind": ""}, {"name": "listTags()", "description": "Retrieves the list of available tags for filtering recipes.", "scope": "", "scopeKind": ""}, {"name": "listCuisines()", "description": "Retrieves the list of available cuisines for filtering recipes.", "scope": "", "scopeKind": ""}, {"name": "delay(ms = 300)", "scope": "", "scopeKind": "", "description": "unavailable"}], "calls": ["isMockEnabled", "apiRequest", "delay"], "search-terms": ["recipes", "mockRecipes", "listRecipes", "getRecipe", "saveRecipe", "listTags", "listCuisines", "recipe"], "state": 2, "file_id": 28, "knowledge_revision": 94, "git_revision": "", "revision_history": [{"90": ""}, {"94": ""}], "ctags": [{"_type": "tag", "name": "delay", "path": "/home/kavia/workspace/code-generation/recipe-explorer-171627-171654/recipe_frontend/src/api/recipes.js", "pattern": "/^function delay(ms = 300) {$/", "language": "JavaScript", "kind": "function", "signature": "(ms = 300)"}, {"_type": "tag", "name": "getRecipe", "path": "/home/kavia/workspace/code-generation/recipe-explorer-171627-171654/recipe_frontend/src/api/recipes.js", "pattern": "/^export async function getRecipe(id) {$/", "language": "JavaScript", "kind": "function", "signature": "(id)"}, {"_type": "tag", "name": "listCuisines", "path": "/home/kavia/workspace/code-generation/recipe-explorer-171627-171654/recipe_frontend/src/api/recipes.js", "pattern": "/^export async function listCuisines() {$/", "language": "JavaScript", "kind": "function", "signature": "()"}, {"_type": "tag", "name": "listRecipes", "path": "/home/kavia/workspace/code-generation/recipe-explorer-171627-171654/recipe_frontend/src/api/recipes.js", "pattern": "/^export async function listRecipes(params = {}) {$/", "language": "JavaScript", "kind": "function", "signature": "(params = {})"}, {"_type": "tag", "name": "listTags", "path": "/home/kavia/workspace/code-generation/recipe-explorer-171627-171654/recipe_frontend/src/api/recipes.js", "pattern": "/^export async function listTags() {$/", "language": "JavaScript", "kind": "function", "signature": "()"}, {"_type": "tag", "name": "mockRecipes", "path": "/home/kavia/workspace/code-generation/recipe-explorer-171627-171654/recipe_frontend/src/api/recipes.js", "pattern": "/^const mockRecipes = [$/", "language": "JavaScript", "kind": "constant"}, {"_type": "tag", "name": "saveRecipe", "path": "/home/kavia/workspace/code-generation/recipe-explorer-171627-171654/recipe_frontend/src/api/recipes.js", "pattern": "/^export async function saveRecipe(recipe) {$/", "language": "JavaScript", "kind": "function", "signature": "(recipe)"}], "hash": "ddc85a2065474e5d59dc4911e597286f", "format-version": 4, "code-base-name": "recipe_frontend", "filename": "recipe_frontend/src/api/recipes.js"}